tgf/__init__.py
tgf/cli.py
tgf/config.py
tgf/tgf.py
tgf-0.1.0.dist-info/DESCRIPTION.rst
tgf-0.1.0.dist-info/METADATA
tgf-0.1.0.dist-info/RECORD
tgf-0.1.0.dist-info/WHEEL
tgf-0.1.0.dist-info/entry_points.txt
tgf-0.1.0.dist-info/metadata.json
tgf-0.1.0.dist-info/top_level.txt
