Metadata-Version: 2.0
Name: tgf
Version: 0.1.0
Summary: Typecraft Graph Format
Home-page: https://github.com/Typecraft/tgf
Author: Tormod Haugland
Author-email: tormod.haugland@gmail.com
License: MIT license
Keywords: tgf
Platform: UNKNOWN
Classifier: Development Status :: 2 - Pre-Alpha
Classifier: Intended Audience :: Developers
Classifier: License :: OSI Approved :: MIT License
Classifier: Natural Language :: English
Classifier: Programming Language :: Python :: 2
Classifier: Programming Language :: Python :: 2.7
Classifier: Programming Language :: Python :: 3
Classifier: Programming Language :: Python :: 3.3
Classifier: Programming Language :: Python :: 3.4
Classifier: Programming Language :: Python :: 3.5
Requires-Dist: Click (>=6.0)
